[
  {
    "ApiId": "/providers/microsoft.powerapps/apis/shared_sharepointonline",
    "CdpRevision": {
      "BaseUrl": "/",
      "LastChangedTimeString": "2021-04-29T16:33:13.5830000Z",
      "RevisionNumber": 1
    },
    "ConnectedDataSourceInfoNameMapping": {
      "{Attachments}": "Attachments",
      "{Attachments}@odata.type": "{Attachments} ({Attachments}@odata.type)",
      "{FilenameWithExtension}": "File name with extension",
      "{FullPath}": "Full Path",
      "{HasAttachments}": "Has attachments",
      "{Identifier}": "Identifier",
      "{IsFolder}": "IsFolder",
      "{Link}": "Link to item",
      "{ModerationComment}": "Comments associated with the content approval of this list item",
      "{ModerationStatus}": "Content approval status",
      "{Name}": "Name",
      "{Path}": "Folder path",
      "{Thumbnail}": "Thumbnail",
      "{TriggerWindowEndToken}": "Trigger Window End Token",
      "{TriggerWindowStartToken}": "Trigger Window Start Token",
      "{VersionNumber}": "Version number",
      "ApprovalNumber": "ApprovalNumber",
      "ApprovalStatus": "ApprovalStatus",
      "Author": "CreatedBy",
      "Author#Claims": "CreatedBy Claims",
      "bank": "bank",
      "bankaccount": "bankaccount",
      "Capacity": "Capacity",
      "commercial": "commercial",
      "ComplianceAssetId": "Compliance Asset Id",
      "Contractor": "Contractor",
      "ContractorsNumber": "ContractorsNumber",
      "cordinates": "cordinates",
      "Created": "Created",
      "DateAssignedToPE": "DateAssignedToPE",
      "dateInspected": "dateInspected",
      "District": "District",
      "District#Id": "District Id",
      "Editor": "ModifiedBy",
      "Editor#Claims": "ModifiedBy Claims",
      "Feed": "Feed",
      "Feedback": "Feedback",
      "Feeder": "Feeder",
      "HeadOfGroup": "HeadOfGroup",
      "HOGroup": "HOGroup",
      "HOGroup#Claims": "HOGroup Claims",
      "ID": "ID",
      "InjSubstation": "InjSubstation",
      "LengthOfCable": "LengthOfCable",
      "meter": "meter",
      "MIS": "MIS",
      "Modified": "Modified",
      "Others": "Others",
      "projectEngineer": "ProjectEngineer",
      "projectEngineer#Claims": "ProjectEngineer Claims",
      "ProjectEngineerEmail": "ProjectEngineerEmail",
      "ProjectLocation": "ProjectLocation",
      "ProjectNumber": "ProjectNumber",
      "ProjectType": "ProjectType",
      "ProjectType#Id": "ProjectType Id",
      "projID": "projID",
      "SizeOfCable": "SizeOfCable",
      "Status": "ProjectStatus",
      "Teamlead": "Teamlead",
      "Teamlead#Claims": "Teamlead Claims",
      "Timeline": "Timeline",
      "Title": "ProjectName",
      "TypeOfCable": "TypeOfCable",
      "VRatio": "VtRatio",
      "VRatio#Id": "VtRatio Id"
    },
    "DatasetName": "https://ekedp.sharepoint.com/sites/OptechApp",
    "EncodeDataset": true,
    "IsSampleData": false,
    "IsWritable": true,
    "Name": "CommissionedProjects",
    "Type": "ConnectedDataSourceInfo"
  }
]